dataroid/__init__.py
dataroid/dataroid.py
dataroid-0.0.4.dist-info/METADATA
dataroid-0.0.4.dist-info/WHEEL
dataroid-0.0.4.dist-info/top_level.txt
dataroid-0.0.4.dist-info/RECORD
