Metadata-Version: 2.1
Name: dataroid
Version: 0.0.4
Summary: A Simple Wrapper For Synthetic Data Generation
Author: torchd3v
Author-email: <burak96egeli@gmail.com>
Keywords: python,data,generate,synthetic,deep learning,model
Classifier: Development Status :: 1 - Planning
Classifier: Intended Audience :: Developers
Classifier: Programming Language :: Python :: 3
Classifier: Operating System :: Unix
Classifier: Operating System :: MacOS :: MacOS X
Classifier: Operating System :: Microsoft :: Windows
Requires-Dist: pandas (==1.5.3)
Requires-Dist: ctgan (==0.7.1)
